Workbook

Sheet Rating
B2: YES Bank Collection Agency Audit
B5: Version | C5: Ver.2
B6: Agency Name | D6: Agency Location | F6: Agency Address
B7: Audit Date | D7: Audit Period | F7: Audit Firm Name | G7: Kumar Gaurav Agarwal & Company
B8: CM Name | D8: CCL Name | F8: Auditor Name/Contact#
B9: CM Employee ID | D9: CCL Employee ID | E9: NA
B10: Products for which agency does collections | C10: Retail Collection | D10: Agency person with whom the discussion were held
B13: Agency Audit Score
B14: Final Audit Score | C14: Actual | D14: Weightage | E14: Percantage | F14: Grade
B16: Blue book,Receipt Book and ID Card | C16: =Agency!J29 -> 30 | D16: 30 | E16: =C16/D16 -> 1
B17: Allocation,Call Recording ,Target Letter & Vendor Performance Report | C17: =Agency!J47 -> 30 | D17: 30 | E17: =C17/D17 -> 1
B18: System Security | C18: =Agency!J58 -> 30 | D18: 30 | E18: =C18/D18 -> 1
B19: Insurance, Shop Establishment Certificate and Code of conduct | C19: =Agency!J61 -> 5 | D19: 5 | E19: =C19/D19 -> 1
B20: Infrastructure & Other | C20: =Agency!J69 -> 5 | D20: 5 | E20: =C20/D20 -> 1
B21: Total Score | C21: =SUM(C16:C20) -> 100 | D21: =SUM(D16:D20) -> 100 | E21: =C21/D21 -> 1 | F21: =IF(ROUNDUP(E21,2)<60%,"C",IF(ROUNDUP(E21,2)<70%,"C+",IF(ROUNDUP(E21,2)<80%,"B",IF(ROUNDUP(E21,2)<90%,"B+",IF(ROUNDUP(E21,2)<100%,"A","A+"))))) -> A+
B22: Final Rating on Agency Audit | C22: =VLOOKUP($F$21,$C$27:$D$33,2,FALSE) -> Excellent
B26: Scoring and Grade Matrix
B27: Score | C27: Grade | D27: Performance
B28: 100 | C28: A+ | D28: Excellent
B29: 90-99 | C29: A | D29: Very Good
B30: 80-89 | C30: B+ | D30: Good
B31: 70-79 | C31: B | D31: Satisfactory
B32: 60-69 | C32: C+ | D32: Unsatisfactory
B33: 59 and Below | C33: C | D33: Poor

Sheet Agency
A1: Sr. No. | B1: Main category | C1: Check points Category | D1: Risk Level | E1: Details to be checked | F1: Points to be checked | G1: Scoring Parameter | H1: Complied (Yes/No) | I1: No. of Errors | J1: Score | K1: Clarification | L1: Observations | M1: Revert from the CM | N1: Revert from the Auditor | O1: Annx.
A2: 1 | B2: AGREEMENT COPY | C2: Agreement & rate annexure | D2: High | E2: Whether the vendor agreement and the latest rate annexures maintained at the agency? Whether the Code of Conduct poster is displayed at the agency? | F2: 1) Agreement has to be signed by both the parties i.e Bank and Agency. | G2: Done : 10 else : 0 | H2: Yes | I2: NA | J2: =IF(H2="NA","NA",IF(H2="Yes",10,0)) -> 10 | K2: Detailed observations needs to be updated here. And details of missing documents or any other pendency should be updated in the Annexure sheet | L2: Yes, Compete vendor agreement is maintained at the agency
A3: 2 | B3: AGREEMENT COPY | C3: Agreement & rate annexure | D3: High | E3: Whether the vendor agreement and the latest rate annexures maintained at the agency? Whether the Code of Conduct poster is displayed at the agency? | F3: 2) If supplementary agreement the scope of work for Retails Collections needs to there. | G3: Done : 10 else : 0 | H3: Yes | I3: NA | J3: =IF(H3="NA","NA",IF(H3="Yes",10,0)) -> 10 | K3: Detailed observations needs to be updated here. And details of missing documents or any other pendency should be updated in the Annexure sheet | L3: Yes, Compete agreement is maintained at the agency
A4: 3 | B4: AGREEMENT COPY | C4: Agreement & rate annexure | D4: High | E4: Whether the vendor agreement and the latest rate annexures maintained at the agency? Whether the Code of Conduct poster is displayed at the agency? | F4: 3) Latest rate annexure | G4: Done : 10 else : 0 | H4: Yes | I4: NA | J4: =IF(H4="NA","NA",IF(H4="Yes",10,0)) -> 10 | K4: Detailed observations needs to be updated here. And details of missing documents or any other pendency should be updated in the Annexure sheet | L4: Yes, latest rate annexures maintained at the agency
A5: 4 | B5: AGREEMENT COPY | C5: Agreement & rate annexure | D5: High | E5: Whether the vendor agreement and the latest rate annexures maintained at the agency? Whether the Code of Conduct poster is displayed at the agency? | F5: 4) COC should be signed and displayed. | G5: Done : 10 else : 0 | H5: Yes | I5: NA | J5: =IF(H5="NA","NA",IF(H5="Yes",10,0)) -> 10 | K5: Detailed observations needs to be updated here. And details of missing documents or any other pendency should be updated in the Annexure sheet | L5: Yes, Code of Conduct poster is displayed at the agency
A6: 5 | B6: BLUEBOOK | C6: Hygiene | D6: High | E6: Whether blue book formats are filled completely & correctly by the agencies . | F6: 1) Code of Conduct page should be signed by agency's owner. | G6: Done: 10 else 2 for each such case | H6: Yes | I6: NA | J6: =IF(H6="NA","NA",IF(H6="Yes",10,IF(I6=1,8,IF(I6=2,6,IF(I6=3,4,IF(I6=4,2,IF(I6>=4,0))))))) -> 10 | L6: Blue book formats are filled completely/correctly by the agency
A7: 6 | B7: BLUEBOOK | C7: Hygiene | D7: High | E7: Whether blue book formats are filled completely & correctly by the agencies . | F7: 2) Declaration cum undertaking page owners/CP signature should be filled up in blue book. | G7: Done: 10 else 2 for each such case | H7: Yes | I7: NA | J7: =IF(H7="NA","NA",IF(H7="Yes",10,IF(I7=1,8,IF(I7=2,6,IF(I7=3,4,IF(I7=4,2,IF(I7>=4,0))))))) -> 10 | L7: Blue book formats are filled completely/correctly by the agency
A8: 7 | B8: BLUEBOOK | C8: Hygiene | D8: High | E8: Whether blue book formats are filled completely & correctly by the agencies . | F8: 3)Data purging declaration should be filled up completely in blue book. | G8: Done: 10 else 2 for each such case | H8: Yes | I8: NA | J8: =IF(H8="NA","NA",IF(H8="Yes",10,IF(I8=1,8,IF(I8=2,6,IF(I8=3,4,IF(I8=4,2,IF(I8>=4,0))))))) -> 10 | L8: Blue book formats are filled completely/correctly by the agency
A9: 8 | B9: BLUEBOOK | C9: Hygiene | D9: High | E9: Whether blue book formats are filled completely & correctly by the agencies . | F9: 4)Computer Declaration in Infrastructure details should be filled properly. | G9: Done: 10 else 2 for each such case | H9: Yes | I9: NA | J9: =IF(H9="NA","NA",IF(H9="Yes",10,IF(I9=1,8,IF(I9=2,6,IF(I9=3,4,IF(I9=4,2,IF(I9>=4,0))))))) -> 10 | L9: Blue book formats are filled completely/correctly by the agency
A10: 9 | B10: BLUEBOOK | C10: Hygiene | D10: High | E10: Whether blue book formats are filled completely & correctly by the agencies . | F10: 5)Telephone Declaration in Infrastructure details should be filled up properly. | G10: Done: 10 else 2 for each such case | H10: Yes | I10: NA | J10: =IF(H10="NA","NA",IF(H10="Yes",10,IF(I10=1,8,IF(I10=2,6,IF(I10=3,4,IF(I10=4,2,IF(I10>=4,0))))))) -> 10 | L10: Blue book formats are filled completely/correctly by the agency
A11: 10 | B11: BLUEBOOK | C11: Hygiene | D11: High | E11: Whether blue book formats are filled completely & correctly by the agencies . | F11: 6) Agency manpower register should be filled up properly and completely and ID card details should be matched with bank record. | G11: Done: 10 else 2 for each such case | H11: Yes | I11: NA | J11: =IF(H11="NA","NA",IF(H11="Yes",10,IF(I11=1,8,IF(I11=2,6,IF(I11=3,4,IF(I11=4,2,IF(I11>=4,0))))))) -> 10 | L11: Blue book formats are filled completely/correctly by the agency
A12: 11 | B12: BLUEBOOK | C12: Hygiene | D12: High | E12: Whether blue book formats are filled completely & correctly by the agencies . | F12: 7) Receipt book issuance register should be filled up properly and completely and should be matched with bank record. | G12: Done: 10 else 2 for each such case | H12: NA | I12: NA | J12: =IF(H12="NA","NA",IF(H12="Yes",10,IF(I12=1,8,IF(I12=2,6,IF(I12=3,4,IF(I12=4,2,IF(I12>=4,0))))))) -> NA | L12: Na as no physical receipt books are issued to the agency for the Audit period
A13: 12 | B13: BLUEBOOK | C13: Hygiene | D13: High | E13: Whether blue book formats are filled completely & correctly by the agencies . | F13: 8) Agency training tracker should be filled up by CP/RCM if training has been provided. | G13: Done: 10 else 2 for each such case | H13: Yes | I13: NA | J13: =IF(H13="NA","NA",IF(H13="Yes",10,IF(I13=1,8,IF(I13=2,6,IF(I13=3,4,IF(I13=4,2,IF(I13>=4,0))))))) -> 10 | L13: Blue book formats are filled completely/correctly by the agency
A14: 13 | B14: BLUEBOOK | C14: Hygiene | D14: High | E14: Whether blue book formats are filled completely & correctly by the agencies . | F14: 9) Billing tracker should be filled up completely in Blue book. | G14: Done: 10 else 2 for each such case | H14: Yes | I14: NA | J14: =IF(H14="NA","NA",IF(H14="Yes",10,IF(I14=1,8,IF(I14=2,6,IF(I14=3,4,IF(I14=4,2,IF(I14>=4,0))))))) -> 10 | L14: Blue book formats are filled completely/correctly by the agency
A15: 14 | B15: BLUEBOOK | C15: Hygiene | D15: High | E15: Whether blue book formats are filled completely & correctly by the agencies . | F15: 10) Repokit tracker should be filled up and matched with bank record applicable only for repo agency. | G15: Done: 10 else 2 for each such case | H15: NA | I15: NA | J15: =IF(H15="NA","NA",IF(H15="Yes",10,IF(I15=1,8,IF(I15=2,6,IF(I15=3,4,IF(I15=4,2,IF(I15>=4,0))))))) -> NA | L15: Na as no Repokit are issued to the agency for the Audit period
A16: 15 | B16: BLUEBOOK | C16: Visitor Register | D16: Low | E16: Whether agency maintains visitor register in blue book at their office ? Also, check if Collection Partner (CP) / Regional Collection Manager (RCM) visiting the agency signs the visiting register maintained at the agency? | F16: 1) Copy of visitor register needs to be taken during audit. | G16: Done : 10 else : 0 | H16: Yes | I16: NA | J16: =IF(H16="NA","NA",IF(H16="Yes",10,0)) -> 10 | L16: Blue book formats are filled completely/correctly by the agency
A17: 16 | B17: BLUEBOOK | C17: Register | D17: Medium | E17: 1. Whether physical receipt books are issued to the agency. 2. Whether agency has maintained and submitted the receipt reconciliation to the Bank? | F17: 1) Please cross tally physical receipt book register maintained at agency with Central Team data? | G17: Done : 10 else : reduce 5 for each error | H17: NA | I17: NA | J17: =IF(H17="NA","NA",IF(H17="Yes",10,IF(I17=1,5,0))) -> NA | L17: Na as no physical receipt books are issued to the agency for the Audit period
A18: 17 | B18: BLUEBOOK | C18: Register | D18: Medium | E18: 1. Whether physical receipt books are issued to the agency. 2. Whether agency has maintained and submitted the receipt reconciliation to the Bank? | F18: 2) Please check agency has maintained physical receipt book reconciliation statement if agency has used physical receipt book.Also cross check whrther agency has sent reconcillation statement to bank on monthly basis via mail. | G18: Done : 10 else : reduce 5 for each error | H18: NA | I18: NA | J18: =IF(H18="NA","NA",IF(H18="Yes",10,IF(I18=1,5,0))) -> NA | L18: Na as no physical receipt books are issued to the agency for the Audit period
A19: 18 | B19: RECEIPT BOOK | C19: Register | D19: Medium | E19: 1.Whether cash collected is deposited in Time? | F19: Please check receipt date and deposition date mentioned in receipt reconcillation MIS and also cross check batch id/hand off sheet/ CAPS Deposition Memo | G19: Done: 10 else: -2 for each case of deposition >= 2 days (without any justification) Critical: -10 if delay> 5days or any case of non deposition | H19: NA | I19: NA | J19: =IF(H19="NA","NA",IF(H19="Yes",10,IF(H19="Critical",-10,IF(I19=1,-2,IF(I19=2,-4,IF(I19=3,-6,IF(I19=4,-8,-10))))))) -> NA | K19: Agencies / In-house team should deposit the collected payments in designated our Bank branches within 24 hours of collection. | L19: NA as, During the audit review for the current quarter, it has been verified that no cash collection has been carried out by the designated agency
A20: 19 | B20: RECEIPT BOOK | C20: Issuance | D20: High | E20: 1.Please comment about the process of filling in the receipts (completely and correctly and without cuttings/alterations/ over writing on the receipts). 2.Do all cancelled receipts have all Four copies with the branch (Also check for hologram in cancelled receipts)? 3.Hologram needs to be tamperred on all cancelled and expired receipts. 4.Does the branch have FIR copies,indemnity bond and newspaper advertisement cutout for lost receipts ? 5.Whether the agencies managed by the Collection Partner (CP) have returned the expired/used receipt books as per process. Also applicable for the in-house books used by the Collection Partner (CP) 6.Whether all unused receipt books are in safe custody of agency's authorized person or not? | F20: 1.Please comment about the process of filling in the receipts (completely and correctly and without cuttings/alterations/ over writing on the receipts). | G20: Done : 10 else : 0 | H20: NA | I20: NA | J20: =IF(H20="NA","NA",IF(H20="Yes",10,0)) -> NA | L20: NA as, During the audit review for the current quarter, it has been verified that no cash collection has been carried out by the designated agency
A21: 20 | B21: RECEIPT BOOK | C21: Issuance | D21: High | E21: 1.Please comment about the process of filling in the receipts (completely and correctly and without cuttings/alterations/ over writing on the receipts). 2.Do all cancelled receipts have all Four copies with the branch (Also check for hologram in cancelled receipts)? 3.Hologram needs to be tamperred on all cancelled and expired receipts. 4.Does the branch have FIR copies,indemnity bond and newspaper advertisement cutout for lost receipts ? 5.Whether the agencies managed by the Collection Partner (CP) have returned the expired/used receipt books as per process. Also applicable for the in-house books used by the Collection Partner (CP) 6.Whether all unused receipt books are in safe custody of agency's authorized person or not? | F21: 2.Do all cancelled receipts have all Four copies with the branch (Also check for hologram in cancelled receipts)? | G21: Done : 10 else : 0 | H21: NA | I21: NA | J21: =IF(H21="NA","NA",IF(H21="Yes",10,0)) -> NA | L21: NA as, During the audit review for the current quarter, it has been verified that no cash collection has been carried out by the designated agency
A22: 21 | B22: RECEIPT BOOK | C22: Issuance | D22: High | E22: 1.Please comment about the process of filling in the receipts (completely and correctly and without cuttings/alterations/ over writing on the receipts). 2.Do all cancelled receipts have all Four copies with the branch (Also check for hologram in cancelled receipts)? 3.Hologram needs to be tamperred on all cancelled and expired receipts. 4.Does the branch have FIR copies,indemnity bond and newspaper advertisement cutout for lost receipts ? 5.Whether the agencies managed by the Collection Partner (CP) have returned the expired/used receipt books as per process. Also applicable for the in-house books used by the Collection Partner (CP) 6.Whether all unused receipt books are in safe custody of agency's authorized person or not? | F22: 3.Hologram needs to be tamperred on all cancelled and expired receipts. | G22: Done : 10 else : 0 | H22: NA | I22: NA | J22: =IF(H22="NA","NA",IF(H22="Yes",10,0)) -> NA | L22: NA as, During the audit review for the current quarter, it has been verified that no cash collection has been carried out by the designated agency
A23: 22 | B23: RECEIPT BOOK | C23: Issuance | D23: High | E23: 1.Please comment about the process of filling in the receipts (completely and correctly and without cuttings/alterations/ over writing on the receipts). 2.Do all cancelled receipts have all Four copies with the branch (Also check for hologram in cancelled receipts)? 3.Hologram needs to be tamperred on all cancelled and expired receipts. 4.Does the branch have FIR copies,indemnity bond and newspaper advertisement cutout for lost receipts ? 5.Whether the agencies managed by the Collection Partner (CP) have returned the expired/used receipt books as per process. Also applicable for the in-house books used by the Collection Partner (CP) 6.Whether all unused receipt books are in safe custody of agency's authorized person or not? | F23: 4.Does the branch have FIR copies,indemnity bond and newspaper advertisement cutout for lost receipts ? | G23: Done : 10 else : 0 | H23: NA | I23: NA | J23: =IF(H23="NA","NA",IF(H23="Yes",10,0)) -> NA | L23: NA as, During the audit review for the current quarter, it has been verified that no cash collection has been carried out by the designated agency
A24: 23 | B24: RECEIPT BOOK | C24: Issuance | D24: High | E24: 1.Please comment about the process of filling in the receipts (completely and correctly and without cuttings/alterations/ over writing on the receipts). 2.Do all cancelled receipts have all Four copies with the branch (Also check for hologram in cancelled receipts)? 3.Hologram needs to be tamperred on all cancelled and expired receipts. 4.Does the branch have FIR copies,indemnity bond and newspaper advertisement cutout for lost receipts ? 5.Whether the agencies managed by the Collection Partner (CP) have returned the expired/used receipt books as per process. Also applicable for the in-house books used by the Collection Partner (CP) 6.Whether all unused receipt books are in safe custody of agency's authorized person or not? | F24: 5.Whether the agencies managed by the Collection Partner (CP) have returned the expired/used receipt books as per process. Also applicable for the in-house books used by the Collection Partner (CP) | G24: Done : 10 else : 0 | H24: NA | I24: NA | J24: =IF(H24="NA","NA",IF(H24="Yes",10,0)) -> NA | L24: NA as, During the audit review for the current quarter, it has been verified that no cash collection has been carried out by the designated agency
A25: 24 | B25: RECEIPT BOOK | C25: Issuance | D25: High | E25: 1.Please comment about the process of filling in the receipts (completely and correctly and without cuttings/alterations/ over writing on the receipts). 2.Do all cancelled receipts have all Four copies with the branch (Also check for hologram in cancelled receipts)? 3.Hologram needs to be tamperred on all cancelled and expired receipts. 4.Does the branch have FIR copies,indemnity bond and newspaper advertisement cutout for lost receipts ? 5.Whether the agencies managed by the Collection Partner (CP) have returned the expired/used receipt books as per process. Also applicable for the in-house books used by the Collection Partner (CP) 6.Whether all unused receipt books are in safe custody of agency's authorized person or not? | F25: 6.Whether all unused receipt books are in safe custody of agency's authorized person or not? | G25: Done : 10 else : 0 | H25: NA | I25: NA | J25: =IF(H25="NA","NA",IF(H25="Yes",10,0)) -> NA | L25: NA as, During the audit review for the current quarter, it has been verified that no cash collection has been carried out by the designated agency
A26: 25 | B26: ID CARD | C26: ID card and Manpower | D26: High | E26: Whether all the Field Executives are DRA certified and have valid digital ID card issued by Yes Bank? | F26: 1)ID card need to be generated live during audit visit and also take screenshots of all ID card isssued by bank. | G26: Done: 10 else: -2 for each case of non compliance | H26: Yes | I26: NA | J26: =IF(H26="NA","NA",IF(H26="Yes",10,IF(I26=1,-2,IF(I26=2,-4,IF(I26=3,-6,IF(I26=4,-8,-10)))))) -> 10 | L26: Yes, All Field Executives are DRA certified and hold valid digital ID cards issued by Yes Bank as per policy requirements.
A27: 26 | B27: DRA | C27: Telecaller | D27: High | E27: Whether all Callers working in agency are DRA certified? | F27: Please take screenshots of all DRA certificate of Telecaller working for YBL. | G27: Done: 10 else: -2 for each case of non compliance | H27: Yes | I27: NA | J27: =IF(H27="NA","NA",IF(H27="Yes",10,IF(I27=1,-2,IF(I27=2,-4,IF(I27=3,-6,IF(I27=4,-8,-10)))))) -> 10 | L27: Yes, All Callers employed by the agency are DRA certified in accordance with regulatory and institutional requirements.
A28: 27 | B28: ID CARD | C28: ID card and Manpower | D28: High | E28: Whether all ID cards where executives have been resigned/terminated are submitted to CP/Central Processing Team and same has been updated in ID card tracker of bluebook or not? | F28: Whether all ID cards where executives have been resigned/terminated are submitted to CP/Central Processing Team and same has been updated in ID card tracker of bluebook or not? | G28: Done: 10 else 2 for each such case | H28: NA | I28: NA | J28: =IF(H28="NA","NA",IF(H28="Yes",10,IF(I28=1,8,IF(I28=2,6,IF(I28=3,4,IF(I28=4,2,0)))))) -> NA | L28: NA as no Such case was observed for the audit period
A29: A | E29: Sub-Total | J29: =(SUM(J2:J28)/(COUNT(J2:J28)*10)*30) -> 30
A30: 28 | B30: ALLOCATION | C30: Y CAPS | D30: Medium | E30: Whether agency is using Y CAPS to download allocation and if they are able to download allocation cases on Y CAPS? Whether the allocation downloaded by CAPS is matching with the allocation sent by the Bank? | F30: 1) Auditor should do live checking of Y CAPS Allocation download at the time of audit. | G30: Done: 10 else: -2 for each case of non compliance | H30: Yes | I30: NA | J30: =IF(H30="NA","NA",IF(H30="Yes",10,IF(I30=1,-2,IF(I30=2,-4,IF(I30=3,-6,IF(I30=4,-8,-10)))))) -> 10 | L30: Yes, the same has been compiled by the agency as per Bank Process
A31: 29 | B31: ALLOCATION | C31: Y CAPS | D31: Medium | E31: Whether agency is using Y CAPS to download allocation and if they are able to download allocation cases on Y CAPS? Whether the allocation downloaded by CAPS is matching with the allocation sent by the Bank? | F31: 2) Cross tally allocation downloaded on caps with allocation available in system as well as allocation provided by Central team for audit purpose. | G31: Done: 10 else: -2 for each case of non compliance | H31: Yes | I31: NA | J31: =IF(H31="NA","NA",IF(H31="Yes",10,IF(I31=1,-2,IF(I31=2,-4,IF(I31=3,-6,IF(I31=4,-8,-10)))))) -> 10 | L31: Yes, the same has been compiled by the agency as per Bank Process
A32: 30 | B32: ALLOCATION | C32: Allocation mappin with ID Card | D32: High | E32: Whether All allocations is allocated to Valid ID card holder person only? | F32: Please check allocation file and cross check whether all cases have been mapped against valid ID card holder.Details should be captured if any discrepancy observed. | G32: Done: 10 else: -2 for each case of non compliance | H32: Yes | I32: NA | J32: =IF(H32="NA","NA",IF(H32="Yes",10,IF(I32=1,-2,IF(I32=2,-4,IF(I32=3,-6,IF(I32=4,-8,-10)))))) -> 10 | K32: Agency should follow M Caps app as digital drive for receipt recording i.e. used/unused/cancelled status of receipt Agency should submit M Caps receipt cancellation documents to central team. | L32: Yes, the same has been compiled by the agency as per Bank Process
A33: 31 | B33: ALLOCATION | C33: Marc ID | D33: High | E33: 1) Whether agency is updating CAPS system for receipt recording i.e. used/unused/cancelled status of receipt? 2.Whether all the FOS has MCAPS ID’s and are active? | F33: Please do live checking related to trail updation and receipt making process.Screenshot of all FOS's Marc id is required. | G33: Done: 10 else 2 for each such case | H33: NA | I33: NA | J33: =IF(H33="NA","NA",IF(H33="Yes",10,IF(I33=1,8,IF(I33=2,6,IF(I33=3,4,IF(I33=4,2,0)))))) -> NA | L33: NA as, During the audit review for the current quarter, it has been verified that no cash collection has been carried out by the designated agency
A34: 32 | B34: ALLOCATION | C34: Marc ID | D34: High | E34: 1) Whether agency is updating CAPS system for receipt recording i.e. used/unused/cancelled status of receipt? 2.Whether all the FOS has MCAPS ID’s and are active? | F34: Whether all the FOS has MCAPS ID’s and are active? | G34: Done: 10 else 2 for each such case | H34: NA | I34: NA | J34: =IF(H34="NA","NA",IF(H34="Yes",10,IF(I34=1,8,IF(I34=2,6,IF(I34=3,4,IF(I34=4,2,0)))))) -> NA | L34: NA as, During the audit review for the current quarter, it has been verified that no cash collection has been carried out by the designated agency
A35: 33 | B35: ALLOCATION | C35: Trails | D35: High | E35: Whether the agency is following up on the allocation sent by the Bank and If the allocation matches with the same sent by Bank? How is pan India allocation managed if any agency has allocation for multiple locations? | F35: Calling feedback and visit feedback should be checked for all allocated cases to agency. | G35: Done: 10 else 2 for each such case | H35: Yes | I35: NA | J35: =IF(H35="NA","NA",IF(H35="Yes",10,IF(I35=1,8,IF(I35=2,6,IF(I35=3,4,IF(I35=4,2,0)))))) -> 10 | K35: Pls impact score if trails uploaded is <70% or PTP is >=98% | L35: Yes, Calling feedback and visit feedback are recorded by the agency for their allotted cases
A36: 34 | B36: ALLOCATION | C36: Trails Updation in Y CAPS | D36: High | E36: Whether 100% trails uploaded by agency in Y CAPS for allocated cases for a particular month? Whether all allocated cases have feedback? | F36: Please do live checking related to trail updation process in Y CAPS.Also do sample checking of trail in CAPS | G36: Done : 10 else : 0 Critical: -10 if calling facility is not available | H36: Yes | I36: NA | J36: =IF(H36="NA","NA",IF(H36="Yes",10,IF(H36="critical",-10,0))) -> 10 | L36: Yes, the same has been compiled by the agency as per Bank Process
A37: 35 | B37: CALL RECORDING | C37: Telephone Etiquette | D37: High | E37: Whether telephone etiquette is followed in calls ? Also, check whether telecallers using pseudo names ? | F37: Please check sample calls for allocated cases and captured details in annexure. | G37: Done: 10 else: -2 for each case of non compliance | H37: Yes | I37: NA | J37: =IF(H37="NA","NA",IF(H37="Yes",10,IF(I37=1,-2,IF(I37=2,-4,IF(I37=3,-6,IF(I37=4,-8,-10)))))) -> 10 | K37: All registered phone nos. should only be used for calling & should have recording facility In addition : 1. Agency should not confirm the settlement amount to the customer, it subject should be subject to approval 2. Any rude call / harsh tone (like abusive language used) during the call 3. Any impersonation by caller / FOS as police / lawyer / media etc., | L37: Yes, Code of Conduct guidelines was followed by telecaller during the call to customer
A38: 36 | B38: CALL RECORDING | C38: Call Recording Data | D38: Medium | E38: Whether Call recording facility available at the agency & 100% call recordings were done ? | F38: 1)Call recording instrumet should be available at agency and it should be in working condition. | G38: Done : 10 else : -2 for each month | H38: Yes | I38: NA | J38: =IF(H38="NA","NA",IF(H38="Critical",-10,IF(H38="Yes",10,IF(I38=1,-2,IF(I38=2,-4,IF(I38=3,-6,IF(I38=4,-8,-10))))))) -> 10 | L38: Yes, Call recording facility available at the agency & 100% call recordings were done
A39: 37 | B39: CALL RECORDING | C39: Call Recording Data | D39: Medium | E39: Whether Call recording facility available at the agency & 100% call recordings were done ? | F39: 2) Live calling should be checked at the time of agency visit. | G39: Done : 10 else : -2 for each month | H39: Yes | I39: NA | J39: =IF(H39="NA","NA",IF(H39="Critical",-10,IF(H39="Yes",10,IF(I39=1,-2,IF(I39=2,-4,IF(I39=3,-6,IF(I39=4,-8,-10))))))) -> 10 | L39: Yes, Live call recording facility available and working at the time of audit
A40: 38 | B40: CALL RECORDING | C40: Call Recording Data | D40: Medium | E40: Whether Call recording facility available at the agency & 100% call recordings were done ? | F40: 3 )Customers are contacted only between 8 am to 7 pm . In case of deviations same is to be highlighted in the audit observations | G40: Done : 10 else : -2 for each month | H40: Yes | I40: NA | J40: =IF(H40="NA","NA",IF(H40="Critical",-10,IF(H40="Yes",10,IF(I40=1,-2,IF(I40=2,-4,IF(I40=3,-6,IF(I40=4,-8,-10))))))) -> 10 | L40: Yes, Calling was done by the agency as per COC guidelines
A41: 39 | B41: CALL RECORDING | C41: Call Recording Data | D41: Medium | E41: Whether Call recording facility available at the agency & 100% call recordings were done ? | F41: 4) Call intensity to be checked for allocated cases. | G41: Done : 10 else : -2 for each month | H41: Yes | I41: NA | J41: =IF(H41="NA","NA",IF(H41="Critical",-10,IF(H41="Yes",10,IF(I41=1,-2,IF(I41=2,-4,IF(I41=3,-6,IF(I41=4,-8,-10))))))) -> 10 | L41: Yes, Call intensity was followed by the agency as per COC guidelines
A42: 40 | B42: CALL RECORDING | C42: Call Recording Data | D42: Low | E42: Whether call recording data is maintained for minimum 12 months by the agencies ? Also, check whether agencies have back-up of the call recording data. Please check Total no of calls made across portfolio in audit period. | F42: Please make annexure for calling counts in audit period. | G42: Done : 10 else : reduce 1 each error Critical: -10 if not documented | H42: Yes | I42: NA | J42: =IF(H42="NA","NA",IF(H42="Critical",-10,IF(H42="Yes",10,IF(I42=1,-2,IF(I42=2,-4,IF(I42=3,-6,IF(I42=4,-8,-10))))))) -> 10 | K42: In addition : 1. Pls check that the agency should be able to retrieve call recordings within 20 mins. | L42: Yes, Call recording data are available with agency for 12 months
A43: 41 | B43: TARGETSETTING LETTER | C43: TargetSetting letter | D43: Medium | E43: Whether Target setting letters are documented with complete & correct details? | F43: 1)Please check count of cases mentioned in target letter and cross check with count of llocation as per bank record for the period mentioned on target setting letter. | G43: Done : 10 else : -2 for each month | H43: Yes | I43: NA | J43: =IF(H43="NA","NA",IF(H43="Critical",-10,IF(H43="Yes",10,IF(I43=1,-2,IF(I43=2,-4,IF(I43=3,-6,IF(I43=4,-8,-10))))))) -> 10 | K43: Target setting letter of a particular month should be documented by 5th of same month. | L43: Yes, Target setting letters are maintain by the agency as per Bank policy
A44: 42 | B44: TARGETSETTING LETTER | C44: TargetSetting letter | D44: Medium | E44: Whether Target setting letters are documented with complete & correct details? | F44: 2) Please check agency sign and stamp along with CP sign on target letter. | G44: Done : 10 else : -2 for each month | H44: Yes | I44: NA | J44: =IF(H44="NA","NA",IF(H44="Critical",-10,IF(H44="Yes",10,IF(I44=1,-2,IF(I44=2,-4,IF(I44=3,-6,IF(I44=4,-8,-10))))))) -> 10 | K44: Target setting letter of a particular month should be documented by 5th of same month. | L44: Yes, Target setting letters are maintain by the agency with complete and correct details
A45: 43 | B45: VENDOR PERFORMANCE REPORT | C45: Vendor Performance Report | D45: Medium | E45: Whether monthly vendor performance review is documented with complete & correct details & preventive measures have been taken by agency based on review ? | F45: 1)Please check No. of cases,POS value with bank data and target resolution,Normalization,Roll back with Month end status file shared by CP. | G45: Done : 10 else : -2 for each month | H45: Yes | I45: NA | J45: =IF(H45="NA","NA",IF(H45="Critical",-10,IF(H45="Yes",10,IF(I45=1,-2,IF(I45=2,-4,IF(I45=3,-6,IF(I45=4,-8,-10))))))) -> 10 | K45: Pls check for VEF submitted on or before 15th of the month, Pls cross check the declaration & documentation by the CP regarding call recording facility, trails upload, Data purging etc. | L45: Yes, monthly vendor performance are maintain by the agency as per Bank policy
A46: 44 | B46: VENDOR PERFORMANCE REPORT | C46: Vendor Performance Report | D46: Medium | E46: Whether monthly vendor performance review is documented with complete & correct details & preventive measures have been taken by agency based on review ? | F46: 2) Please check agency sign and stamp along with CP sign on target letter. | G46: Done : 10 else : -2 for each month | H46: Yes | I46: NA | J46: =IF(H46="NA","NA",IF(H46="Critical",-10,IF(H46="Yes",10,IF(I46=1,-2,IF(I46=2,-4,IF(I46=3,-6,IF(I46=4,-8,-10))))))) -> 10 | K46: Pls check for VEF submitted on or before 15th of the month, Pls cross check the declaration & documentation by the CP regarding call recording facility, trails upload, Data purging etc. | L46: Yes, monthly vendor performance are maintain by the agency with complete and correct details
A47: B | E47: Sub-Total | J47: =(SUM(J30:J46)/(COUNT(J30:J46)*10)*30) -> 30
A48: 45 | B48: SYSTEM & SECURITY | C48: Data security | D48: High | E48: Whether any agency found not complied to USB/CD/Floppy drive active for data transfer ? | F48: Data Cable access should be deactive for data transfer./USB Port should be deactive for data transfer. | G48: Done 10, else -5 for each non-compliance | H48: Yes | I48: NA | J48: =IF(H48="NA","NA",IF(H48="Yes",10,IF(I48=1,-5,IF(I48=2,-10,IF(I48=3,-15,-20))))) -> 10 | K48: USB/CD/floppy drive should not be active for data transfer | L48: Yes, USB/CD/Floppy drive was inactive for data transfer at agency for allotted system
A49: 46 | B49: SYSTEM & SECURITY | C49: Data security | D49: High | E49: Whether agency has purged data as per bank's policy ? | F49: Auditor to check agency systems & confirm : All customer confidential data (which includes contact details, PAN number, email id, mother maiden name, bank account number etc.) is deleted after 3 months.Agency has to maintain 4 months(Incluiding current month) demographic data of YBL. Pls also check if demographic detail of customers are available on mail. Physical data storage(Drawer,Cupboard etc) at agency to be checked during audit. System data and SOA shall be checked at agencies. | G49: Done : 10 else : -10 | H49: Yes | I49: NA | J49: =IF(H49="NA","NA",IF(H49="Yes",10,-10)) -> 10 | L49: Yes, the same has been compiled by the agency as per Bank Process
A50: 47 | B50: SYSTEM & SECURITY | C50: Data security | D50: High | E50: Whether e-mail & printer access is available with executives ? Whether restricted access of Desktop / laptops/ Printers/ emails are enabled? | F50: 1)E-mail and printer access should be given only on backend system only. | G50: Done 10, else -5 for each non-compliance | H50: Yes | I50: NA | J50: =IF(H50="NA","NA",IF(H50="Yes",10,IF(I50=1,-5,IF(I50=2,-10,IF(I50=3,-15,-20))))) -> 10 | L50: Yes, the same has been compiled by the agency as per Bank Process
A51: 48 | B51: SYSTEM & SECURITY | C51: Data security | D51: High | E51: Whether e-mail & printer access is available with executives ? Whether restricted access of Desktop / laptops/ Printers/ emails are enabled? | F51: 2)Mail ID could not be shared with other organization | G51: Done 10, else -5 for each non-compliance | H51: Yes | I51: NA | J51: =IF(H51="NA","NA",IF(H51="Yes",10,IF(I51=1,-5,IF(I51=2,-10,IF(I51=3,-15,-20))))) -> 10 | L51: Yes, the same has been compiled by the agency as per Bank Process
A52: 49 | B52: SYSTEM & SECURITY | C52: Data security | D52: High | E52: Whether e-mail & printer access is available with executives ? Whether restricted access of Desktop / laptops/ Printers/ emails are enabled? | F52: 3) Customer data access should be restricted for 3 months | G52: Done 10, else -5 for each non-compliance | H52: Yes | I52: NA | J52: =IF(H52="NA","NA",IF(H52="Yes",10,IF(I52=1,-5,IF(I52=2,-10,IF(I52=3,-15,-20))))) -> 10 | L52: Yes, the same has been compiled by the agency as per Bank Process
A53: 50 | B53: SYSTEM & SECURITY | C53: Data security | D53: High | E53: Whether e-mail & printer access is available with executives ? Whether restricted access of Desktop / laptops/ Printers/ emails are enabled? | F53: 4)Unauthorized access should not be with agency executive | G53: Done 10, else -5 for each non-compliance | H53: Yes | I53: NA | J53: =IF(H53="NA","NA",IF(H53="Yes",10,IF(I53=1,-5,IF(I53=2,-10,IF(I53=3,-15,-20))))) -> 10 | L53: Yes, the same has been compiled by the agency as per Bank Process
A54: 51 | B54: SYSTEM & SECURITY | C54: Data security | D54: High | E54: Whether e-mail & printer access is available with executives ? Whether restricted access of Desktop / laptops/ Printers/ emails are enabled? | F54: 5) Customer demog / financial details should only in password protected attachment & not on the mail body. | G54: Done 10, else -5 for each non-compliance | H54: Yes | I54: NA | J54: =IF(H54="NA","NA",IF(H54="Yes",10,IF(I54=1,-5,IF(I54=2,-10,IF(I54=3,-15,-20))))) -> 10 | L54: Yes, the same has been compiled by the agency as per Bank Process
A55: 52 | B55: SYSTEM & SECURITY | C55: Data security | D55: High | E55: Whether any agency found not complied to other Data security / safety / privacy / sharing policy of the bank ? Whether data shared through mail are password protected ? | F55: Anydesk , Team-viewer, Dropbox, whatsapp Application should not be installed on control panel. | G55: Done 10, else -5 for each non-compliance | H55: Yes | I55: NA | J55: =IF(H55="NA","NA",IF(H55="Yes",10,IF(I55=1,-5,IF(I55=2,-10,IF(I55=3,-15,-20))))) -> 10 | K55: Agency preferably has to do white listing of email address such that emails can be sent only to authorized email id's, such as Yesbank.in domain. In absence of whitelisting of email address, agency should provide declaration for using the registered email id exclusively for Yesbank | L55: Yes, the same has been compiled by the agency as per Bank Process
A56: 53 | B56: SYSTEM & SECURITY | C56: Data privacy | D56: High | E56: Whether agency has email access through which customer data can be shared to any email id?Whether any commuication sent to on unregistered mail ID by Agency ? Has the agency done white listing of email address such that emails can be sent only to authorized email id's, such as YESBANK.IN | F56: No decalaration is accepted if agency is using any public domain id such as gmail,yahoo,etc. | G56: Done 10, else -5 for each non-compliance | H56: Yes | I56: NA | J56: =IF(H56="NA","NA",IF(H56="Yes",10,-10)) -> 10 | K56: 1. Customers info., documents, records & assets of the bank is kept separately & confidential 2. Also, pls check if any common folder or server access. In such case, the bank's data should be password protected 3. Common folder / server file access should only be available with authorized agency executives 4. Also, please check that labeling the PC / Laptop used for Yes Bank & declaration in blue book. | L56: Yes, the same has been compiled by the agency as per Bank Process
A57: 54 | B57: SYSTEM & SECURITY | C57: Data privacy | D57: High | E57: Whether separate system, place & e-mail ID for Yes bank is provided? Also, Check If the Yes Bank labeling is done on system used for Yes Bank and if declaration details are updated in the blue book | F57: Whether separate system, place & e-mail ID for Yes bank is provided? Also, Check If the Yes Bank labeling is done on system used for Yes Bank and if declaration details are updated in the blue book | G57: Done 10, else -5 for each non-compliance | H57: Yes | I57: NA | J57: =IF(H57="NA","NA",IF(H57="Yes",10,-10)) -> 10 | L57: Yes, the same has been compiled by the agency as per Bank Process
A58: C | E58: Sub-Total | J58: =(SUM(J48:J57)/(COUNT(J48:J57)*10)*30) -> 30
A59: 55 | B59: INSURANCE | C59: Insurance Policy | D59: High | E59: Whether Fidelity insurance(cash in transit & cash in safe) is available at the Agency ? Is it Valid ? | F59: Please check insurance validity date,agency name and address on insurance copy | G59: Done 10, else -5 for each non-compliance | H59: Yes | I59: NA | J59: =IF(H59="NA","NA",IF(H59="Yes",10,-10)) -> 10 | L59: Yes, Valid Fidelity insurance(cash in transit & cash in safe) is available at the Agency
A60: 56 | B60: SHOP ESTABLISHMENT CERTIFICATE | C60: Agency establishment | D60: Low | E60: Whether agencies have shop establishment certificate ?IF not check Declaration. | F60: Please check agency name and address mentioned on shop establishment copy. | G60: Done 10, else -5 for each non-compliance | H60: Yes | I60: NA | J60: =IF(H60="NA","NA",IF(H60="Yes",10,-10)) -> 10 | L60: Yes, Shop establishment certificate is available with agency
A61: D | E61: Sub-Total | J61: =(SUM(J59:J60)/(COUNT(J59:J60)*10)*5) -> 5
A62: 57 | B62: INFRASTRUCTURE & OTHER | C62: our bank's reference made on co's name board | D62: High | E62: Has the agency made any reference to our Bank's name on the company's name board.? | F62: Has the agency made any reference to our Bank's name on the company's name board.? | G62: Done : 10 else : -2 for each month | H62: Yes | I62: NA | J62: =IF(H62="NA","NA",IF(H62="Critical",-10,IF(H62="Yes",10,IF(I62=1,-2,IF(I62=2,-4,IF(I62=3,-6,IF(I62=4,-8,-10))))))) -> 10 | K62: Pls also check whether the Infrastructure like PC / Laptop , document storage, FOS etc. are used exclusively for our Bank & not mixed with others. | L62: Yes, the same has been compiled by the agency as per Bank Process
A63: 58 | B63: INFRASTRUCTURE & OTHER | C63: Agency details update in ERP | D63: High | E63: Whether agency's address & phone number are correctly updated on YES BANK website.Www.yesbank.in/regulatory_policies | F63: Whether agency's address & phone number are correctly updated on YES BANK website.Www.yesbank.in/regulatory_policies | G63: Done : 10 else : 0 | H63: Yes | I63: NA | J63: =IF(H63="NA","NA",IF(H63="Yes",10,0)) -> 10 | K63: Auditor to check on the web site and confirm . | L63: Yes, agency's address & phone number are correctly updated on Yes Bank web site
A64: 59 | B64: INFRASTRUCTURE & OTHER | C64: Bill | D64: Low | E64: Whether Copy of Monthly bill is available at agency? Is There Any Pending Bill ? (If Yes Mention Details).Billing to be checked as per pickup and collection agency payment Grid | F64: Whether Copy of Monthly bill is available at agency? Is There Any Pending Bill ? (If Yes Mention Details).Billing to be checked as per pickup and collection agency payment Grid | G64: Done : 10 else : 0 | H64: Yes | I64: NA | J64: =IF(H64="NA","NA",IF(H64="Yes",10,0)) -> 10 | K64: As per the Grid pickup and collection agency needs to be paid separetly | L64: Yes, Copy of Monthly bill is available at agency
A65: 60 | B65: INFRASTRUCTURE & OTHER | C65: No Dues Certificate related | D65: High | E65: Whether NDC is provided by the agency for previous quarter bills that have been paid?Copy of NDC to be maintained with the agency | F65: Whether NDC is provided by the agency for previous quarter bills that have been paid?Copy of NDC to be maintained with the agency | G65: Done : 10 else : 0 | H65: Yes | I65: NA | J65: =IF(H65="NA","NA",IF(H65="Yes",10,0)) -> 10 | K65: As per process agency is required to give "No due certificate" for payout given to agency. | L65: Yes, NDC for the Last quarter is available at agency
A66: 61 | B66: INFRASTRUCTURE & OTHER | C66: Not cooperated with Auditor | D66: Medium | E66: Whether full cooperation/complete & timely data was received from agency for completing audit? | F66: Whether full cooperation/complete & timely data was received from agency for completing audit? | G66: Done 10, else -5 for each non-compliance | H66: Yes | I66: NA | J66: =IF(H66="NA","NA",IF(H66="Yes",10,-5)) -> 10 | K66: Pls impact score if the agency pre-scheduled & intimated is cancelled on the day / a day before visit. | L66: Yes, Full cooperation/complete & timely data was received from agency for completing the audit
A67: 62 | B67: INFRASTRUCTURE & OTHER | C67: Non compliance of last month's audit observation. | D67: Medium | E67: Whether non-compliance reported in the previous period adhered to? | F67: Whether non-compliance reported in the previous period adhered to? | G67: As per audit observation | H67: Yes | I67: NA | J67: =IF(H67="NA","NA",IF(H67="Yes",10,0)) -> 10 | L67: Yes, non-compliance reported in the previous period are rectified and not observed for the current audit period
A68: 63 | B68: INFRASTRUCTURE & OTHER | C68: Additional point | D68: Low | E68: Any other comment which Auditor wants to give | F68: Any other comment which Auditor wants to give | H68: NA | I68: NA | J68: NA | L68: No comment, No Additional case/observation was observed for the audit period
A69: E | E69: Sub-Total | J69: =(SUM(J62:J68)/(COUNT(J62:J68)*10)*5) -> 5

Sheet KAF
A1: Sr. No | B1: Main Category | C1: Check Points Category | D1: Zone | E1: State | F1: Location | G1: CM Name | H1: Employee ID | I1: Observations | J1: Sub Remarks | K1: Loan Account No. | L1: Customer Name | M1: Vendor Name | N1: Executive Name | O1: ID Card No. | P1: Repo-Kit No. | Q1: Repo Date | R1: Godown Name | S1: Godown Location | T1: Sale / Release Date | U1: Sale / Release Amount | V1: Category Of Mismatch | W1: Mismatch Details | X1: Repokit Return Date | Y1: Valuation Dt -Valuation Report | Z1: Valuation Date-Yards Register | AA1: Type Of Executive | AB1: Rcu Positive (Yes/No) | AC1: Dra Trained (Yes/No/Na)

Sheet Annexure 1
A1: Annexure To Form Part Of Agency Report :
A3: Sr No | B3: Name of FOS | C3: ID Card No | D3: Source of information (Telephonic/ Personal Interaction) | E3: Product | F3: Trained on code of conduct | G3: Holding valid id card | H3: Remark

Sheet Annexure 2
A1: Annexure :Call Recording Sampling Data
A3: Sr. No. | B3: Product | C3: LAN | D3: Customer Name | E3: Call Recording available (Y/N) | F3: REMARKS

Sheet Anexure 3
A1: Annexure : Receipt Recording Status
A3: SR. No | B3: Receipt no. | C3: Updated in Y CAPS(Yes/No) | D3: Remarks
A4: NA, No such cases were found during audit period.

Sheet Annexure-4
A1: Annexure : Call Recording Count
A3: Product | B3: January'26 | C3: Februay'26 | D3: March'26

Sheet Annexure-5
A1: Non ID Card Allocation Details :
A3: Month | B3: Product | C3: LAN | D3: CP Name | E3: Non ID Card Executive name
